MANIFEST.in
README.md
setup.py
livebridge/__init__.py
livebridge/bridge.py
livebridge/components.py
livebridge/config.py
livebridge/controller.py
livebridge/loader.py
livebridge/logger.py
livebridge/run.py
livebridge.egg-info/PKG-INFO
livebridge.egg-info/SOURCES.txt
livebridge.egg-info/dependency_links.txt
livebridge.egg-info/entry_points.txt
livebridge.egg-info/not-zip-safe
livebridge.egg-info/requires.txt
livebridge.egg-info/top_level.txt
livebridge/base/__init__.py
livebridge/base/converters.py
livebridge/base/posts.py
livebridge/base/sources.py
livebridge/base/targets.py
livebridge/controldata/__init__.py
livebridge/controldata/base.py
livebridge/controldata/controlfile.py
livebridge/controldata/dynamo.py
livebridge/controldata/storage.py
livebridge/storages/__init__.py
livebridge/storages/base.py
livebridge/storages/dummy.py
livebridge/storages/dynamo.py
livebridge/storages/mongo.py
livebridge/storages/sql.py
livebridge/web/__init__.py
livebridge/web/static/index.html
livebridge/web/static/lb.css
livebridge/web/static/lb.js
livebridge/web/static/vendor/axios-0.17.1.min.js
livebridge/web/static/vendor/bootstrap-4.0.0-beta.3.min.css
livebridge/web/static/vendor/bootstrap-4.0.0-beta.3.min.js
livebridge/web/static/vendor/jquery-3.2.1.slim.min.js
livebridge/web/static/vendor/popper-1.12.9.js
livebridge/web/static/vendor/vue-v2.5.13.min.js