Metadata-Version: 1.1
Name: livebridge
Version: 0.24.0
Summary: Keep content in-sync across services. Or simply syndicate content to multiple services. Based on asyncio.
Home-page: https://github.com/dpa-newslab/livebridge
Author: Martin Borho
Author-email: martin@borho.net
License: Apache Software License (http://www.apache.org/licenses/LICENSE-2.0)
Keywords: liveticker,liveblog,syndication,async,asyncio
Platform: UNKNOWN
Classifier: Programming Language :: Python :: 3.5
Classifier: Topic :: Communications :: Chat
Classifier: Development Status :: 5 - Production/Stable
Classifier: License :: OSI Approved :: Apache Software License
Classifier: Intended Audience :: Other Audience
Classifier: Operating System :: POSIX :: Linux
Classifier: Environment :: Console
